LICENSE
MANIFEST.in
README.rst
setup.py
wagtail_sentiment.egg-info/PKG-INFO
wagtail_sentiment.egg-info/SOURCES.txt
wagtail_sentiment.egg-info/dependency_links.txt
wagtail_sentiment.egg-info/not-zip-safe
wagtail_sentiment.egg-info/requires.txt
wagtail_sentiment.egg-info/top_level.txt
wagtailsentiment/__init__.py
wagtailsentiment/wagtail_hooks.py
wagtailsentiment/static/api-monkeypatch.js
wagtailsentiment/static/wagtailsentiment.bundle.js