Metadata-Version: 1.0
Name: wagtail-sentiment
Version: 1.1.1
Summary: Apply sentiment analysis to rich text content.
Home-page: http://github.com/vixdigital/wagtail-sentiment
Author: VIX Digital
Author-email: info@vix.digital
License: MIT
Platform: UNKNOWN
